{"colors.added":"Barva pro přidané prostředky","colors.conflict":"Barva pro prostředky s konflikty","colors.deleted":"Barva odstraněných prostředků","colors.incomingAdded":"Barva příchozích přidaných prostředků","colors.incomingDeleted":"Barva příchozích odstraněných prostředků","colors.incomingModified":"Barva příchozích upravených prostředků","colors.incomingRenamed":"Barva příchozích přejmenovaných prostředků","colors.modified":"Barva upravených prostředků","colors.possibleConflict":"Barva prostředků s možnými konflikty","colors.workspaceRepositoriesView.hasUncommittedChanges":"Barva úložišť pracovních prostorů, která mají nepotvrzené změny","commands.addRepositoryToWorkspace":"Přidat úložiště do pracovního prostoru...","commands.applyPatch":"Importovat změny...","commands.category":"Vzdálená úložiště","commands.clone":"Místně klonovat úložiště a otevřít na ploše...","commands.commit":"Potvrdit změny a vložit","commands.commitEmpty":"Potvrdit prázdné a nasdílet změny","commands.configureIndexingAllowedRepos":"Konfigurovat indexování úložišť","commands.continueEditSession.clone.qualifiedName":"Pokračovat v práci v novém místním klonu","commands.continueEditSession.openOnDesktop.qualifiedName":"Pokračovat v práci ve vzdáleném úložišti na ploše VS Code","commands.continueEditSession.openOnWeb":"Otevřít na webu","commands.continueEditSession.openOnWeb.qualifiedName":"Pokračovat v práci v VS Code pro web","commands.continueOn":"Pokračovat v práci...","commands.continueOn.addRepositoryToWorkspace":"Přidat úložiště GitHub do pracovního prostoru...","commands.continueOn.openRepository":"Otevřít vzdálené úložiště...","commands.copyVscodeDevLink":"Kopírovat odkaz vscode.dev","commands.createBranch":"Vytvořit novou větev...","commands.createBranchFrom":"Vytvořit novou větev z...","commands.createDraftPullRequest":"Vytvořit koncept žádosti o přijetí změn","commands.createPullRequest":"Vytvořit žádost o přijetí změn","commands.deleteAllLocalRepositoryData":"Odstranit všechny indexy úložiště","commands.deleteLocalRepositoryData":"Odstranit index úložiště...","commands.disableDebugLogging":"Zakázat protokolování ladění","commands.disableIndexingForSession":"Dočasně zakázat indexování","commands.discardAllChanges":"Zahodit všechny změny","commands.discardChanges":"Zahodit změny","commands.enableDebugLogging":"Povolit protokolování ladění","commands.enableIndexing":"Povolit indexování úložiště","commands.exportDebugInfo":"Exportovat informace o ladění","commands.exportPatch":"Exportovat změny...","commands.fetch":"Načíst změny","commands.goToRepository":"Přejít na úložiště","commands.keepChanges":"_Zachovat změny","commands.notebook.continueOn":"Pokračovat v práci...","commands.openChanges":"Otevřít změny","commands.openFile":"Otevřít soubor","commands.openOnDesktop":"Znovu otevřít virtuální úložiště na ploše","commands.openOnRemote":"Otevřít v GitHubu","commands.openOnWeb":"Otevřít na webu","commands.openRepository":"Otevřít vzdálené úložiště...","commands.pull":"Přijmout změny","commands.refresh":"Aktualizovat","commands.remoteHelp.getStarted":"Začínáme","commands.stageAllChanges":"Připravit všechny změny","commands.stageChanges":"Připravit změny","commands.switchToBranch":"Přepnout na větev...","commands.sync":"Synchronizovat (přijmout a nasdílet změny)","commands.timeline.compareWithSelected":"Porovnat s vybraným","commands.timeline.copyCommitId":"Kopírovat ID potvrzení změn","commands.timeline.copyCommitMessage":"Kopírovat zprávu potvrzení","commands.timeline.openDiff":"Otevřít změny","commands.timeline.openOnAzureRepos":"Otevřít v Azure Repos","commands.timeline.openOnGitHub":"Otevřít v GitHubu","commands.timeline.selectForCompare":"Vybrat pro porovnání","commands.unstageAllChanges":"Zrušit přípravu všech změn","commands.unstageChanges":"Zrušit přípravu změn","commands.views.workspaceRepositories.applyAllChanges":"Použít všechny změny","commands.views.workspaceRepositories.applyChanges":"Použít změny","commands.views.workspaceRepositories.open":"Otevřít pracovní prostor","commands.views.workspaceRepositories.openChanges":"Otevřít změny","commands.views.workspaceRepositories.openFile":"Otevřít soubor","commands.views.workspaceRepositories.openInNewWindow":"Otevřít pracovní prostor v novém okně","commands.views.workspaceRepositories.remove":"Odebrat","config.commitDirectlyWarning":"Určuje, jestli se má zobrazit upozornění, že změny budou odevzdány přímo vzdálenému poskytovateli (např. GitHub).","config.commitDirectlyWarning.always":"Vždy varuje","config.commitDirectlyWarning.auto":"Upozorní na první potvrzení.","config.commitDirectlyWarning.off":"Zakáže upozornění potvrzení.","config.experimental.syncRecentList":"Určuje, jestli se má synchronizovat seznam naposledy otevřených úložišť.","config.experimental.useDiffMatchPatch":"Určuje, jestli se má pro lepší výkon při generování rozdílů v souborech používat knihovna diff-match-patch.","config.gitProtocol":"Určuje, který protokol se používá ke klonování úložiště.","config.logLevel":"Určuje, kolik (pokud nějaké) se má protokolovat do výstupního kanálu _Remote Repositories_","config.logLevel.debug":"Protokolovat všechny chyby, upozornění a zprávy s dodatečným kontextem užitečným pro ladění","config.logLevel.error":"Protokoluje pouze chyby","config.logLevel.info":"Protokolovat všechny chyby, upozornění a zprávy","config.logLevel.off":"Neprotokoluje nic","config.logLevel.warn":"Zapíše do protokolu všechny chyby a upozornění.","config.richNavigation.enabled":"Určuje, jestli se má povolit rozšířená navigace, pokud je úložiště indexované","config.richNavigation.indexMode":"Určuje výchozí chování indexu pro větve.","config.richNavigation.indexMode.latest":"Povolí rozšířenou u navigaci u nejnovějšího indexovaného potvrzení větve. Soubory budou jen pro čtení.","config.richNavigation.indexMode.none":"Použití indexu rozšířené navigace je pro větve zakázáno","config.richNavigation.indexMode.tipPlusLatest":"Povolí rozšířenou navigaci v aktuálním potvrzení s použitím nejnovějšího indexu. Do souborů bude možné zapisovat.","config.staging.enabled":"Určuje, jestli se mají povolit přípravné změny před potvrzením.","config.staging.smart":"Určuje, jestli se mají před potvrzením automaticky rozfázovat všechny změny, pokud žádné neexistují.","config.switchToCreatedBranch":"Určuje, jestli se má po vytvoření zobrazit výzva k přepnutí na nově vytvořenou větev.","config.switchToCreatedBranch.always":"Vždy přepnout na nově vytvořenou větev bez zobrazení výzvy","config.switchToCreatedBranch.prompt":"Dotázat se, jestli se má přepnout na nově vytvořenou větev","config.uncommittedChangesOnEntry":"Určuje, co se má udělat při opětovném vstupu do pracovního prostoru, který již obsahuje nepotvrzené změny.","config.uncommittedChangesOnEntry.none":"Nezobrazovat výzvu","config.uncommittedChangesOnEntry.promptIfBehind":"Zobrazit výzvu v případě příchozích změn a také nepotvrzených změn","description":"Vzdálené procházení a úpravy úložišť Git","displayName":"Vzdálená úložiště","submenu.branch":"Větev","submenu.changes":"Změny","submenu.commit":"Potvrzení","submenu.patch":"Import/export","submenu.pullRequest":"Žádost o přijetí změn","views.remote.name":"Vzdálená úložiště","viewsWelcome.debug":"Funkce Spustit a Ladit nejsou ve webovém editoru k dispozici. Pokračujte v prostředí, které může spouštět kód, jako je codespace nebo místní VS Code.","viewsWelcome.debug.continueOn":"Funkce Spustit a Ladit nejsou ve webovém editoru k dispozici. Pokračujte v prostředí, které může spouštět kód, jako je codespace nebo místní VS Code, a převeďte si své pracovní změny s sebou.\n[Pokračovat v práci...](command:remoteHub.continueOn \"Pokračovat v práci na tomto vzdáleném úložišti jinde\")","viewsWelcome.explorer":"Úložiště nebo žádost o přijetí změn můžete vzdáleně otevřít bez klonování.\n[Otevřít vzdálené úložiště](command:remoteHub.openRepository)","viewsWelcome.explorer.web":"Můžete vzdáleně otevřít úložiště nebo žádost o přijetí změn.\n[Otevřít vzdálené úložiště](command:remoteHub.openRepository)","viewsWelcome.remoteExplorer":"Tady se zobrazí vaše nedávno otevřená vzdálená úložiště.\n[Otevřít vzdálené úložiště](command:remoteHub.openRepository)","viewsWelcome.scm.web":"Můžete vzdáleně otevřít úložiště nebo žádost o přijetí změn.\n[Otevřít vzdálené úložiště](command:remoteHub.openRepository)","viewsWelcome.terminal":"Terminály nejsou ve webovém editoru k dispozici. Pokračujte v prostředí, které může spouštět kód, jako je codespace nebo místní VS Code.","viewsWelcome.terminal.continueOn":"Terminály nejsou ve webovém editoru k dispozici. Pokračujte v prostředí, které může spouštět kód, jako je codespace nebo místní VS Code, a převeďte si své pracovní změny s sebou.\n[Pokračovat v práci...](command:remoteHub.continueOn \"Pokračovat v práci na tomto vzdáleném úložišti jinde\")"}
